MANIFEST.in
README.markdown
setup.py
pytest_data/__init__.py
pytest_data/functions.py
pytest_data/plugin.py
pytest_data.egg-info/PKG-INFO
pytest_data.egg-info/SOURCES.txt
pytest_data.egg-info/dependency_links.txt
pytest_data.egg-info/entry_points.txt
pytest_data.egg-info/top_level.txt