Metadata-Version: 1.1
Name: pytest-data
Version: 0.4
Summary: Useful functions for managing data for pytest fixtures
Home-page: https://github.com/horejsek/python-pytest-data
Author: Michal Horejsek
Author-email: horejsekmichal@gmail.com
License: PSF
Platform: UNKNOWN
Classifier: Programming Language :: Python
Classifier: Programming Language :: Python :: 2
Classifier: Programming Language :: Python :: 3
Classifier: License :: OSI Approved :: MIT License
Classifier: Operating System :: OS Independent
Classifier: Development Status :: 5 - Production/Stable
Classifier: Intended Audience :: Developers
Classifier: Topic :: Software Development :: Libraries :: Python Modules
